manyterm/__init__.py
manyterm/manyToOne.py
manyterm/oneToMany.py
manyterm-2.0.0.dist-info/LICENSE
manyterm-2.0.0.dist-info/METADATA
manyterm-2.0.0.dist-info/WHEEL
manyterm-2.0.0.dist-info/top_level.txt
manyterm-2.0.0.dist-info/RECORD
