Metadata-Version: 2.2
Name: manyterm
Version: 2.0.0
Summary: Manyterm - spawn multiple terminals to print to
Author: Tyler Bowers
Author-email: tylerebowers@gmail.com
License: MIT
Project-URL: Source, https://github.com/tylerebowers/manyterm-python
Project-URL: PyPI, https://pypi.org/project/manyterm/
Keywords: python,terminal,print
Classifier: Topic :: Terminals
Classifier: Development Status :: 4 - Beta
Classifier: License :: OSI Approved :: MIT License
Classifier: Programming Language :: Python :: 3
Classifier: Operating System :: OS Independent
Classifier: Intended Audience :: Developers
Classifier: Natural Language :: English
Requires-Python: >=3.8
License-File: LICENSE
Requires-Dist: psutil
Dynamic: author
Dynamic: author-email
Dynamic: classifier
Dynamic: description
Dynamic: description-content-type
Dynamic: keywords
Dynamic: license
Dynamic: project-url
Dynamic: requires-dist
Dynamic: requires-python
Dynamic: summary
